ghcp/__init__.py
ghcp/cli.py
ghcp/core.py
ghcp-0.1.3.dist-info/METADATA
ghcp-0.1.3.dist-info/WHEEL
ghcp-0.1.3.dist-info/entry_points.txt
ghcp-0.1.3.dist-info/licenses/LICENSE
ghcp-0.1.3.dist-info/RECORD
