Metadata-Version: 2.4
Name: ghcp
Version: 0.1.3
Summary: Copy a folder or file from GitHub without cloning (CLI)
Author-email: Your Name <you@example.com>
License: MIT
License-File: LICENSE
Requires-Python: >=3.8
Requires-Dist: requests>=2.28
